Metadata-Version: 2.1
Name: pywall
Version: 0.1.0
Summary: Python firewall framework.
Home-page: https://github.com/Decentra-Network/pywall
Author: Decentra Network Developers
Author-email: onur@decentranetwork.org
License: MIT
Platform: UNKNOWN
Requires-Python: >=3.8
